AUTHORS.rst
CHANGES.rst
COPYING
MANIFEST.in
Makefile
README.rst
pytest.ini
setup.py
tox.ini
PyVantagePro.egg-info/PKG-INFO
PyVantagePro.egg-info/SOURCES.txt
PyVantagePro.egg-info/dependency_links.txt
PyVantagePro.egg-info/entry_points.txt
PyVantagePro.egg-info/not-zip-safe
PyVantagePro.egg-info/requires.txt
PyVantagePro.egg-info/top_level.txt
docs/.gitignore
docs/Makefile
docs/conf.py
docs/index.rst
docs/make.bat
docs/_static/pyvantagepro.jpg
docs/_templates/sidebarintro.html
docs/_themes/.gitignore
docs/_themes/LICENSE
docs/_themes/README
docs/_themes/flask_theme_support.py
docs/_themes/flask_theme_support.pyc
docs/_themes/flask/layout.html
docs/_themes/flask/relations.html
docs/_themes/flask/theme.conf
docs/_themes/flask/static/flasky.css_t
docs/_themes/flask/static/small_flask.css
docs/_themes/flask_small/layout.html
docs/_themes/flask_small/theme.conf
docs/_themes/flask_small/static/flasky.css_t
pyvantagepro/__init__.py
pyvantagepro/__main__.py
pyvantagepro/compat.py
pyvantagepro/device.py
pyvantagepro/logger.py
pyvantagepro/parser.py
pyvantagepro/utils.py
pyvantagepro/tests/__init__.py
pyvantagepro/tests/test_parser.py
pyvantagepro/tests/test_utils.py